Workbook

Sheet Rate Sheet
A3: To Request Emergency Response Services Please Contact Your BioRemedy Representative Or Email The Emergency Response Inbox At ER@BioRemedy.com
A4: Standard Rates | C4: for work performed Monday through Friday between the hours of 8:00 AM and 5:00 PM.
A5: Overtime Rates | C5: for work performed outside the standard work hours and all Saturdays and Sundays.
A6: Emergency Rates | C6: for any work that is considered an emergency regardless of when work is performed.
A7: Double Time Rates | C7: applies to all work performed on a holiday
A8: Holidays are New Years Eve, New Years Day, Easter, Memorial Day, Independence Day, Labor Day, Thanksgiving, Black Friday, Christmas Eve and Christmas Day.
B9: BioRemedy RATE SHEET
A10: ** There is a Four Hour Minimum for Labor, Trucks, & Equipment on Emergency Call Outs **
A11: Section I: Labor Rates | H11: Standard Rate | I11: Emergency/ OT Rate | J11: Double Time Rate | K11: Unit of Measure
A12: Administration | H12: 35 | I12: 35 | J12: 35 | K12: Hourly
A13: Disposal Coordinator | H13: 70 | I13: =IF(ISNUMBER(Sheet5!I13),IFERROR(H13*1.5,Sheet5!I13),Sheet5!I13) -> 105 | J13: =H13*2 -> 140 | K13: Hourly
A14: Site Safety Coordinator | H14: 119 | I14: =IF(ISNUMBER(Sheet5!I15),IFERROR(H14*1.5,Sheet5!I15),Sheet5!I15) -> 178.5 | J14: =H14*2 -> 238 | K14: Hourly
A15: Microbial Consultant | H15: 103 | I15: =IF(ISNUMBER(Sheet5!I16),IFERROR(H15*1.5,Sheet5!I16),Sheet5!I16) -> 154.5 | J15: =H15*2 -> 206 | K15: Hourly
A16: Senior Project Manager/ER Manager/IC | H16: 92 | I16: =IF(ISNUMBER(Sheet5!I17),IFERROR(H16*1.5,Sheet5!I17),Sheet5!I17) -> 138 | J16: =H16*2 -> 184 | K16: Hourly
A17: Supervisor | H17: 85 | I17: =IF(ISNUMBER(Sheet5!I18),IFERROR(H17*1.5,Sheet5!I18),Sheet5!I18) -> 127.5 | J17: =H17*2 -> 170 | K17: Hourly
A18: Foreman | H18: 75 | I18: =IF(ISNUMBER(Sheet5!I19),IFERROR(H18*1.5,Sheet5!I19),Sheet5!I19) -> 112.5 | J18: =H18*2 -> 150 | K18: Hourly
A19: Technician ‐ HazMat trained, Confined Space Certified | H19: 65 | I19: =IF(ISNUMBER(Sheet5!I20),IFERROR(H19*1.5,Sheet5!I20),Sheet5!I20) -> 97.5 | J19: =H19*2 -> 130 | K19: Hourly
A20: Recovery Truck Operator | H20: 83 | I20: =IF(ISNUMBER(Sheet5!I21),IFERROR(H20*1.5,Sheet5!I21),Sheet5!I21) -> 124.5 | J20: =H20*2 -> 166 | K20: Hourly
A21: Heavy Equipment Operator | H21: 75 | I21: =IF(ISNUMBER(Sheet5!I22),IFERROR(H21*1.5,Sheet5!I22),Sheet5!I22) -> 112.5 | J21: =H21*2 -> 150 | K21: Hourly
A22: CDL Truck Driver | H22: 65 | I22: =IF(ISNUMBER(Sheet5!I23),IFERROR(H22*1.5,Sheet5!I23),Sheet5!I23) -> 97.5 | J22: =H22*2 -> 130 | K22: Hourly
A23: Mechanic | H23: 70 | I23: =IF(ISNUMBER(Sheet5!I24),IFERROR(H23*1.5,Sheet5!I24),Sheet5!I24) -> 105 | J23: =H23*2 -> 140 | K23: Hourly
A24: Lodging | H24: 200 | I24: =IF(ISNUMBER(Sheet5!I25),IFERROR(H24*1.5,Sheet5!I25),Sheet5!I25) -> 300 | J24: 300 | K24: Per Man Per Day
A25: Per Diem | H25: 70 | I25: =IF(ISNUMBER(Sheet5!I26),IFERROR(H25*1.5,Sheet5!I26),Sheet5!I26) -> 105 | J25: 100 | K25: Per Man Per Day
A26: Section II: Equipment and Materials (All Fuel Burning Equipment Will Be Subject To A Fuel Surcharge)
A27: Hydro Super Vac | H27: Cost +28% Margin | I27: Cost +28% Margin | J27: Cost+28% Margin | K27: Hourly
A28: Microbial Spray Trailer | H28: =Sheet5!H29*0.9 -> 315 | I28: N/A | J28: N/A | K28: Daily
A29: Environmental CyberResponse Unit | H29: =Sheet5!H30*0.9 -> 270 | I29: N/A | J29: N/A | K29: Daily
A30: HazMat Recovery Truck | H30: 250 | I30: N/A | J30: N/A | K30: Hourly
A31: 3/4 Ton or 1 Ton Pick‐Up Truck | H31: 300 | I31: N/A | J31: N/A | K31: Daily
A32: Pick‐Up Truck (1/2 or smaller) | H32: =Sheet5!H34*0.9 -> 180 | I32: N/A | J32: N/A | K32: Daily
A33: Vactron | H33: 80 | I33: N/A | J33: N/A | K33: Hourly
A34: Toll Tag Fees – Two Axle | H34: Cost + 10% Margin | I34: N/A | J34: N/A | K34: Each
A35: Toll Tag Fees ‐ Four Axels | H35: Cost + 10% Margin | I35: N/A | J35: N/A | K35: Each
A36: Drone Service (includes Operator) | H36: 150 | I36: 150 | J36: 150 | K36: Hourly
A37: Tractor w/ Van Trailer or Flatbed (Includes Operator) | H37: =Sheet5!H38*0.9 -> 117 | I37: 160 | J37: 205 | K37: Hourly
A38: Tractor w/ Dbl Rolloff Trailer | H38: Cost +28% Margin | I38: Cost +28% Margin | J38: Cost +28% Margin | K38: Hourly
A39: BIOREMEDY Bobtail Roll‐Off Truck/Driver (Includes Operator) | H39: =Sheet5!H40*0.9 -> 135 | I39: 185 | J39: 225 | K39: Hourly
A40: BIOREMEDY 100 bbl. Vacuum Truck (Includes Operator) | H40: 155 | I40: 195 | J40: 245 | K40: Hourly
A41: 70 bbl. Vacuum Truck (Includes Operator) | H41: 140 | I41: 175 | J41: 215 | K41: Hourly
A42: Tractor w/ 130 bbl. Vacuum Tanker (Includes Operator) | H42: =Sheet5!H43*0.9 -> 148.5 | I42: 200 | J42: 245 | K42: Hourly
A43: Tractor w/ 130 bbl. FRP Haz Waste Trailer (Includes Operator) | H43: =Sheet5!H44*0.9 -> 144 | I43: 190 | J43: 235 | K43: Hourly
A44: Air Mover / Guzzler / Super Sucker (Includes Operator) BIOREMEDY Owned | H44: =Sheet5!H45*0.9 -> 265.5 | I44: 330 | J44: 370 | K44: Hourly
A45: Washout (Recovery Truck) | H45: =Sheet5!H46*0.9 -> 112.5 | I45: N/A | J45: N/A | K45: Each
A46: Washout for Vacuum Truck (Non Haz) | H46: =Sheet5!H47*0.9 -> 360 | I46: N/A | J46: N/A | K46: Each
A47: Washout for Vacuum Truck (Hazardous) | H47: =Sheet5!H48 -> Cost +28% Margin | I47: Cost +28% Margin | J47: Cost+28% Margin | K47: Each
A48: Drum Truck w/Drum Dolly (Include Operator) | H48: =Sheet5!H49*0.9 -> 126 | I48: 180 | J48: 280 | K48: Hourly
A49: Heavy Equipment
A50: Skid Steer Front Loader (Does Not Include Operator or Trailer) | H50: =Sheet5!H51*0.9 -> 450 | I50: 575 | J50: 575 | K50: Daily
A51: Mini‐Excavator (Does Not Include Operator or Trailer) | H51: =Sheet5!H52*0.9 -> 540 | I51: 675 | J51: 675 | K51: Daily
A52: Skid Steer Attachments (price listed or cost plus 20%) | H52: =Sheet5!H53*0.9 -> 135 | I52: 225 | J52: 225 | K52: Daily
A53: Forklift (does not include pick up or drop off charges) | H53: =Sheet5!H54*0.9 -> 247.5 | I53: 275 | J53: 275 | K53: Daily
A54: 40' Boom Lift (does not include pick up or drop off charges) | H54: =Sheet5!H55*0.9 -> 225 | I54: 350 | J54: 350 | K54: Daily
A55: Trailers
A56: Gooseneck Equipment Tailer | H56: 215 | I56: N/A | J56: N/A | K56: Daily
A57: Bumper Pull Flat Bed trailer | H57: 130 | I57: N/A | J57: N/A | K57: Daily
A58: HazMat Response Trailer/Tools Package | H58: =Sheet5!H60 -> 1000 | I58: N/A | J58: N/A | K58: Daily
A59: Oil Spill Trailer | H59: =Sheet5!H61 -> 600 | I59: N/A | J59: N/A | K59: Daily
A60: Confined Space Rescue Trailer (Includes tri pod w/ winch, 2 harnesses and 2 man rescue gear) | H60: =Sheet5!H62 -> 750 | I60: N/A | J60: N/A | K60: Daily
A61: Dump Trailer | H61: =Sheet5!H63 -> 400 | I61: N/A | J61: N/A | K61: Daily
A62: Flood Water Removal
A63: Air Mover (Floor Dryer) | H63: =Sheet5!H65 -> 25 | I63: N/A | J63: N/A | K63: Daily
A64: Dehumidifier | H64: =Sheet5!H66 -> 110 | I64: N/A | J64: N/A | K64: Daily
A65: Marine Equipment (All Fuel Burning Equipment Will Be Subject To A Fuel Surcharge)
A66: Response Boat w/ Single Engine | H66: =Sheet5!H68 -> 425 | I66: N/A | J66: N/A | K66: Daily
A67: Water Response Boom Trailer | H67: =Sheet5!H69 -> 300 | I67: N/A | J67: N/A | K67: Daily
A68: 10" Containment Boom | H68: =Sheet5!H70 -> 1.3 | I68: N/A | J68: N/A | K68: Per Foot
A69: 18" Containment Boom | H69: =Sheet5!H71 -> 2.1 | I69: N/A | J69: N/A | K69: Per Foot
A70: Drum Skinner | H70: =Sheet5!H72 -> 300 | I70: N/A | J70: N/A | K70: Daily
A71: Pumps and Accessories
A72: 1" Engine Driven Medium-Pressure Diaphragm Pump | H72: =Sheet5!H74 -> 175 | I72: Daily + Rebuild Cost Plus 25% Margin
A73: 1" Air Operated Diaphragm Pump | H73: =Sheet5!H75 -> 175 | I73: Daily + Rebuild Cost Plus 25% Margin
A74: 2" Stainless Steel Air Operated Diaphragm Pump | H74: =Sheet5!H76 -> 225 | I74: Daily + Rebuild Cost Plus 25% Margin
A75: 2" Poly Air Operated Diaphragm Pump | H75: =Sheet5!H77 -> 175 | I75: Daily + Rebuild Cost Plus 25% Margin
A76: 2" Aluminum Air Operated Diaphragm Pump | H76: =Sheet5!H78 -> 200 | I76: Daily + Rebuild Cost Plus 25% Margin
A77: 3" Poly Air Operated Diaphragm Pump | H77: =Sheet5!H79 -> 225 | I77: Daily + Rebuild Cost Plus 25% Margin
A78: 3" Aluminum Air Operated Diaphragm Pump | H78: =Sheet5!H80 -> 275 | I78: Daily + Rebuild Cost Plus 25% Margin
A79: Sump Pump | H79: =Sheet5!H81 -> 50 | I79: Daily
A80: Dura Transfer Pump | H80: =Sheet5!H82 -> 225 | I80: Daily
A81: Disposable Hand Pump | H81: =Sheet5!H83 -> 18 | I81: Each
A82: Hoses/Fittings
A83: 3/8" x 25' Air Hose | H83: =Sheet5!H85 -> 8 | I83: Daily
A84: 3/4" x 50' Air Hose | H84: =Sheet5!H86 -> 22 | I84: Daily
A85: 1" Chemical Suction/Discharge Hose | H85: =Sheet5!H87 -> 2.25 | I85: Per Foot Per Day
A86: 2" Chemical Suction/Discharge Hose | H86: =Sheet5!H88 -> 2.9 | I86: Per Foot Per Day
A87: 2" Suction/Discharge Hose (oil service) | H87: =Sheet5!H89 -> 1.9 | I87: Per Foot Per Day
A88: 3" Suction/Discharge Hose (oil service) | H88: =Sheet5!H90 -> 2.75 | I88: Per Foot Per Day
A89: 4" Suction/Discharge Hose (water service) | H89: =Sheet5!H91 -> 0.75 | I89: Per Foot Per Day
A90: 6" Suction/Discharge Hose (water service) | H90: =Sheet5!H92 -> 0.95 | I90: Per Foot Per Day
A91: 6"x100' ADS hose | H91: =Sheet5!H93 -> Cost + 28% Margin | I91: Based on Market Value
A92: Brass Camlock Fittings Assortment | H92: =Sheet5!H94 -> 100 | I92: Daily
A93: Camlock Fittings Assortment | H93: =Sheet5!H95 -> 50 | I93: Daily
A94: Heavy Duty Garden Hose (3/4"x50') | H94: =Sheet5!H96 -> 15 | I94: Daily
A95: Stainless Steel Camlock Fittings Assortment | H95: =Sheet5!H97 -> 100 | I95: Daily
A96: Generators / Air Compressors
A97: Generator to 5kW | H97: =Sheet5!H99 -> 125 | I97: Daily
A98: Generator 5.1kW to 8kW | H98: =Sheet5!H100 -> 150 | I98: Daily
A99: Generator 8.1kW to 10kW | H99: =Sheet5!H101 -> 175 | I99: Daily
A100: Generator 10.1kW to 15kW | H100: =Sheet5!H102 -> 225 | I100: Daily
A101: HD Extension Cord | H101: =Sheet5!H103 -> 10 | I101: Daily
A102: GFCI | H102: =Sheet5!H104 -> 5 | I102: Daily
...

Sheet Sheet5
A3: To Request Emergency Response Services Please Contact Your BioRemedy Representative Or Email The Emergency Response Inbox At ER@BioRemedy.com
A4: Standard Rates | C4: for work performed Monday through Friday between the hours of 8:00 AM and 5:00 PM.
A5: Overtime Rates | C5: for work performed outside the standard work hours and all Saturday's and Sunday's.
A6: Emergency Rates | C6: for any work that is considered an emergency regardless of when work is performed.
A7: Double Time Rates | C7: applies to all work performed on a holiday
A8: BioRemedy's holidays are New Years Eve, New Years Day, Easter, Memorial Day, Independence Day, Labor Day, Thanksgiving, Black Friday, Christmas Eve and Christmas Day.
A10: ** There is a Four Hour Minimum for Labor, Trucks, & Equipment on Emergency Call Outs **
A11: Section I: Labor Rates | H11: Standard Rate | I11: Emergency/ OT Rate | J11: Double Time Rate | K11: Unit of Measure
A12: Administration | H12: 68 | I12: =H12*1.5 -> 102 | J12: =H12*2 -> 136 | K12: Hourly | M12: =IF(ISNUMBER(I12),IFERROR(H12*1.5,I12),I12) -> 102
A13: Disposal Coordinator | H13: 65 | I13: =H13*1.5 -> 97.5 | J13: =H13*2 -> 130 | K13: Hourly
A14: Resource/Logistics Coordinator | H14: 60 | I14: =H14*1.5 -> 90 | J14: =H14*2 -> 120 | K14: Hourly
A15: Site Safety Coordinator | H15: 110 | I15: =H15*1.5 -> 165 | J15: =H15*2 -> 220 | K15: Hourly
A16: Microbial Consultant | H16: 95 | I16: =H16*1.5 -> 142.5 | J16: =H16*2 -> 190 | K16: Hourly
A17: Senior Project Manager/ER Manager/IC | H17: 85 | I17: =H17*1.5 -> 127.5 | J17: =H17*2 -> 170 | K17: Hourly
A18: Supervisor | H18: 80 | I18: =H18*1.5 -> 120 | J18: =H18*2 -> 160 | K18: Hourly
A19: Foreman | H19: 70 | I19: =H19*1.5 -> 105 | J19: =H19*2 -> 140 | K19: Hourly
A20: Technician ‐ HazMat trained, Confined Space Certified | H20: 60 | I20: =H20*1.5 -> 90 | J20: =H20*2 -> 120 | K20: Hourly
A21: Recovery Truck Operator | H21: 78 | I21: =H21*1.5 -> 117 | J21: =H21*2 -> 156 | K21: Hourly
A22: Heavy Equipment Operator | H22: 80 | I22: =H22*1.5 -> 120 | J22: =H22*2 -> 160 | K22: Hourly
A23: CDL Truck Driver | H23: 75 | I23: =H23*1.5 -> 112.5 | J23: =H23*2 -> 150 | K23: Hourly
A24: Mechanic | H24: 65 | I24: =H24*1.5 -> 97.5 | J24: =H24*2 -> 130 | K24: Hourly
A25: Lodging | H25: 200 | I25: 200 | J25: 300 | K25: Per Man Per Day
A26: Per Diem | H26: 70 | I26: 70 | J26: 100 | K26: Per Man Per Day
A27: Section II: Equipment and Materials (All Fuel Burning Equipment Will Be Subject To A Fuel Surcharge)
A28: Hydro Super Vac | H28: 400 | I28: N/A | J28: N/A | K28: Hourly
A29: Microbial Spray Trailer | H29: 350 | I29: N/A | J29: N/A | K29: Daily
A30: Environmental CyberResponse Unit | H30: 300 | I30: N/A | J30: N/A | K30: Daily
A31: HazMat Recovery Truck | H31: 225 | I31: N/A | J31: N/A | K31: Hourly
A32: Service/Mechanic Truck | H32: 55 | I32: N/A | J32: N/A | K32: Hourly
A33: 3/4 Ton or 1 Ton Pick‐Up/ Dually Truck | H33: 300 | I33: N/A | J33: N/A | K33: Daily
A34: Pick‐Up Truck (1/2 or smaller) | H34: 200 | I34: N/A | J34: N/A | K34: Daily
A35: Vactron | H35: 75 | I35: N/A | J35: N/A | K35: Hourly
A36: Toll Tag Fees – Two Axle | H36: 35 | I36: N/A | J36: N/A | K36: Each
A37: Toll Tag Fees ‐ Four Axels | H37: 55 | I37: N/A | J37: N/A | K37: Each
A38: Tractor w/ Van Trailer or Flatbed (Includes Operator) | H38: 130 | I38: 160 | J38: 205 | K38: Hourly
A39: Tractor w/ Dbl Rolloff Trailer | H39: 135 | I39: 165 | J39: 210 | K39: Hourly
A40: BIOREMEDY Bobtail Roll‐Off Truck/Driver (Includes Operator) | H40: 150 | I40: 185 | J40: 225 | K40: Hourly
A41: 100 bbl. Vacuum Truck (Includes Operator) | H41: 150 | I41: 185 | J41: 225 | K41: Hourly
A42: 70 bbl. Vacuum Truck (Includes Operator) | H42: 140 | I42: 175 | J42: 215 | K42: Hourly
A43: Tractor w/ 130 bbl. Vacuum Tanker (Includes Operator) | H43: 165 | I43: 200 | J43: 245 | K43: Hourly
A44: Tractor w/ 130 bbl. FRP Haz Waste Trailer (Includes Operator) | H44: 160 | I44: 190 | J44: 235 | K44: Hourly
A45: Air Mover / Guzzler / Super Sucker (Includes Operator) BIOREMEDY Owned | H45: 295 | I45: 330 | J45: 370 | K45: Hourly
A46: Washout (Recovery Truck) | H46: 125 | I46: N/A | J46: N/A | K46: Each
A47: Washout for Vacuum Truck (Non Haz) | H47: 400 | I47: N/A | J47: N/A | K47: Each
A48: Washout for Vacuum Truck (Hazardous) | H48: Cost +28% Margin | I48: Cost +28% Margin | J48: Cost+28% Margin | K48: Each
A49: Drum Truck w/Drum Dolly (Include Operator) | H49: 140 | I49: 180 | J49: 280 | K49: Hourly
A50: Heavy Equipment
A51: Skid Steer Front Loader (Does Not Include Trailer) | H51: 500 | I51: 575 | J51: 575 | K51: Daily
A52: Mini‐Excavator (Does Not Include Trailer) | H52: 600 | I52: 675 | J52: 675 | K52: Daily
A53: Skid Steer Attachments | H53: 150 | I53: 225 | J53: 225 | K53: Daily
A54: Forklift | H54: 275 | I54: 275 | J54: 275 | K54: Daily
A55: 40' Boom Lift | H55: 250 | I55: 350 | J55: 350 | K55: Daily
A56: Trailers
A57: Gooseneck Equipment Tailer | H57: 185 | I57: N/A | J57: N/A | K57: Daily
A58: Bumper Pull Flat Bed trailer | H58: 95 | I58: N/A | J58: N/A | K58: Daily
A59: Mobile Boiler | H59: 400 | I59: N/A | J59: N/A | K59: Hourly
A60: HazMat Response Trailer/Tools Package | H60: 1000 | I60: N/A | J60: N/A | K60: Daily
A61: Oil Spill Trailer | H61: 600 | I61: N/A | J61: N/A | K61: Daily
A62: Confined Space Rescue Trailer (Includes tri pod w/ winch, 2 harnesses and 2 man rescue gear) | H62: 750 | I62: N/A | J62: N/A | K62: Daily
A63: Dump Trailer | H63: 400 | I63: N/A | J63: N/A | K63: Daily
A64: Flood Water Removal
A65: Air Mover (Floor Dryer) | H65: 25 | I65: N/A | J65: N/A | K65: Daily
A66: Dehumidifier | H66: 110 | I66: N/A | J66: N/A | K66: Daily
A67: Marine Equipment (All Fuel Burning Equipment Will Be Subject To A Fuel Surcharge)
A68: Response Boat w/ Single Engine | H68: 425 | I68: N/A | J68: N/A | K68: Daily
A69: Water Response Boom Trailer | H69: 300 | I69: N/A | J69: N/A | K69: Daily
A70: 10" Containment Boom | H70: 1.3 | I70: N/A | J70: N/A | K70: Per Foot Per Day
A71: 18" Containment Boom | H71: 2.1 | I71: N/A | J71: N/A | K71: Per Foot Per Day
A72: Drum Skinner | H72: 300 | I72: N/A | J72: N/A | K72: Daily
A73: Pumps and Accessories
A74: 1" Engine Driven Medium-Pressure Diaphragm Pump | H74: 175 | I74: Daily + Rebuild Cost Plus 25% Margin
A75: 1" Air Operated Diaphragm Pump | H75: 175 | I75: Daily + Rebuild Cost Plus 25% Margin
A76: 2" Stainless Steel Air Operated Diaphragm Pump | H76: 225 | I76: Daily + Rebuild Cost Plus 25% Margin
A77: 2" Poly Air Operated Diaphragm Pump | H77: 175 | I77: Daily + Rebuild Cost Plus 25% Margin
A78: 2" Aluminum Air Operated Diaphragm Pump | H78: 200 | I78: Daily + Rebuild Cost Plus 25% Margin
A79: 3" Poly Air Operated Diaphragm Pump | H79: 225 | I79: Daily + Rebuild Cost Plus 25% Margin
A80: 3" Aluminum Air Operated Diaphragm Pump | H80: 275 | I80: Daily + Rebuild Cost Plus 25% Margin
A81: Sump Pump | H81: 50 | I81: Daily
A82: Dura Transfer Pump | H82: 225 | I82: Daily
A83: Disposable Hand Pump | H83: 18 | I83: Each
A84: Hoses/Fittings
A85: 3/8" x 25' Air Hose | H85: 8 | I85: Daily
A86: 3/4" x 50' Air Hose | H86: 22 | I86: Daily
A87: 1" Chemical Suction/Discharge Hose | H87: 2.25 | I87: Per Foot Per Day
A88: 2" Chemical Suction/Discharge Hose | H88: 2.9 | I88: Per Foot Per Day
A89: 2" Suction/Discharge Hose (oil service) | H89: 1.9 | I89: Per Foot Per Day
A90: 3" Suction/Discharge Hose (oil service) | H90: 2.75 | I90: Per Foot Per Day
A91: 4" Suction/Discharge Hose (water service) | H91: 0.75 | I91: Per Foot Per Day
A92: 6" Suction/Discharge Hose (water service) | H92: 0.95 | I92: Per Foot Per Day
A93: 6"x100' ADS hose | H93: Cost + 28% Margin | I93: Based on Market Value
A94: Brass Camlock Fittings Assortment | H94: 100 | I94: Daily
A95: Camlock Fittings Assortment | H95: 50 | I95: Daily
A96: Heavy Duty Garden Hose (3/4"x50') | H96: 15 | I96: Daily
A97: Stainless Steel Camlock Fittings Assortment | H97: 100 | I97: Daily
A98: Generators / Air Compressors
A99: Generator to 5kW | H99: 125 | I99: Daily
A100: Generator 5.1kW to 8kW | H100: 150 | I100: Daily
A101: Generator 8.1kW to 10kW | H101: 175 | I101: Daily
A102: Generator 10.1kW to 15kW | H102: 225 | I102: Daily
A103: HD Extension Cord | H103: 10 | I103: Daily
...
